rotastellar_distributed/__init__.py
rotastellar_distributed/core.py
rotastellar_distributed/federated.py
rotastellar_distributed/mesh.py
rotastellar_distributed/partitioning.py
rotastellar_distributed/sync.py
rotastellar_distributed-0.1.1.dist-info/METADATA
rotastellar_distributed-0.1.1.dist-info/WHEEL
rotastellar_distributed-0.1.1.dist-info/RECORD
