Metadata-Version: 2.4
Name: rotastellar-distributed
Version: 0.1.1
Summary: Distributed compute coordination for Earth-space AI workloads
Project-URL: Homepage, https://rotastellar.com/products/distributed-compute
Project-URL: Documentation, https://docs.rotastellar.com/sdks/python/distributed
Project-URL: Repository, https://github.com/rotastellar/rotastellar-python
Author-email: Subhadip Mitra <subhadipmitra@rotastellar.com>, RotaStellar Research <research@rotastellar.com>
Maintainer-email: Subhadip Mitra <subhadipmitra@rotastellar.com>, RotaStellar Research <research@rotastellar.com>
License: MIT
Keywords: distributed-computing,earth-space-coordination,federated-learning,gradient-compression,model-partitioning,orbital-compute,space
Classifier: Development Status :: 1 - Planning
Classifier: Intended Audience :: Developers
Classifier: Intended Audience :: Science/Research
Classifier: License :: OSI Approved :: MIT License
Classifier: Programming Language :: Python :: 3
Classifier: Topic :: Scientific/Engineering :: Artificial Intelligence
Classifier: Topic :: System :: Distributed Computing
Requires-Python: >=3.9
Requires-Dist: rotastellar>=0.1.0
Provides-Extra: pytorch
Requires-Dist: torch>=2.0; extra == 'pytorch'
Provides-Extra: tensorflow
Requires-Dist: tensorflow>=2.12; extra == 'tensorflow'
